langstruct/__init__.py
langstruct/api.py
langstruct/exceptions.py
langstruct/parallel.py
langstruct/core/__init__.py
langstruct/core/chunking.py
langstruct/core/export_utils.py
langstruct/core/grounding.py
langstruct/core/modules.py
langstruct/core/persistence.py
langstruct/core/refinement.py
langstruct/core/schema_generator.py
langstruct/core/schema_utils.py
langstruct/core/schemas.py
langstruct/core/signatures.py
langstruct/core/validation.py
langstruct/optimizers/__init__.py
langstruct/optimizers/gepa.py
langstruct/optimizers/metrics.py
langstruct/optimizers/mipro.py
langstruct/providers/__init__.py
langstruct/providers/llm_factory.py
langstruct/visualization/__init__.py
langstruct/visualization/html_viz.py
langstruct-0.2.0.dist-info/METADATA
langstruct-0.2.0.dist-info/WHEEL
langstruct-0.2.0.dist-info/licenses/LICENSE
langstruct-0.2.0.dist-info/RECORD
