Metadata-Version: 2.4
Name: langstruct
Version: 0.2.0
Summary: LLM-powered structured information extraction using DSPy optimization
Project-URL: Homepage, https://langstruct.dev
Project-URL: Documentation, https://langstruct.dev
Project-URL: Repository, https://github.com/langstruct-ai/langstruct
Project-URL: Issues, https://github.com/langstruct-ai/langstruct/issues
Project-URL: Changelog, https://github.com/langstruct-ai/langstruct/blob/main/CHANGELOG.md
Author: LangStruct Team
License-Expression: MIT
License-File: LICENSE
Keywords: dspy,extraction,llm,nlp,structured-data
Classifier: Development Status :: 4 - Beta
Classifier: Intended Audience :: Developers
Classifier: License :: OSI Approved :: MIT License
Classifier: Programming Language :: Python :: 3
Classifier: Programming Language :: Python :: 3.12
Classifier: Topic :: Scientific/Engineering :: Artificial Intelligence
Classifier: Topic :: Software Development :: Libraries :: Python Modules
Requires-Python: >=3.12
Requires-Dist: dspy>=3.0.0
Requires-Dist: pydantic>=2.0.0
Requires-Dist: tiktoken>=0.5.0
Requires-Dist: typing-extensions>=4.8.0
Provides-Extra: all
Requires-Dist: black>=23.0.0; extra == 'all'
Requires-Dist: chromadb>=0.4.0; extra == 'all'
Requires-Dist: isort>=5.12.0; extra == 'all'
Requires-Dist: langchain-community>=0.0.10; extra == 'all'
Requires-Dist: langchain-text-splitters>=0.0.1; extra == 'all'
Requires-Dist: mypy>=1.5.0; extra == 'all'
Requires-Dist: openai>=1.0.0; extra == 'all'
Requires-Dist: pre-commit>=3.0.0; extra == 'all'
Requires-Dist: pytest-cov>=4.0.0; extra == 'all'
Requires-Dist: pytest>=7.0.0; extra == 'all'
Requires-Dist: tqdm>=4.66.0; extra == 'all'
Provides-Extra: dev
Requires-Dist: black>=23.0.0; extra == 'dev'
Requires-Dist: isort>=5.12.0; extra == 'dev'
Requires-Dist: mypy>=1.5.0; extra == 'dev'
Requires-Dist: pre-commit>=3.0.0; extra == 'dev'
Requires-Dist: pytest-cov>=4.0.0; extra == 'dev'
Requires-Dist: pytest>=7.0.0; extra == 'dev'
Provides-Extra: examples
Requires-Dist: chromadb>=0.4.0; extra == 'examples'
Requires-Dist: langchain-community>=0.0.10; extra == 'examples'
Requires-Dist: langchain-text-splitters>=0.0.1; extra == 'examples'
Requires-Dist: openai>=1.0.0; extra == 'examples'
Provides-Extra: parallel
Requires-Dist: tqdm>=4.66.0; extra == 'parallel'
